Workbook
Name Kin: donneesVentes!$A$1:$N$9649
Name Segment_Année: #N/A
Name Segment_Produit: #N/A
Name Segment_Produit1: #N/A
Name Segment_Région: #N/A

Sheet Feuil1
A3: Moyenne de Total vente | B3: Étiquettes de colonnes
A4: Étiquettes de lignes | B4: En ligne | C4: En magasin | D4: Sortie | E4: Total général
A5: Lundi | B5: 65793.991 | C5: 235416.67 | D5: 110117.42 | E5: 110381.31
A6: Mardi | B6: 51314.331 | C6: 239090.91 | D6: 114494.7 | E6: 104894.16
A7: Mercredi | B7: 53471.533 | C7: 229281.91 | D7: 108429.7 | E7: 107522.6
A8: Jeudi | B8: 64893.111 | C8: 322692.31 | D8: 132372.86 | E8: 130290.6
A9: Vendredi | B9: 77202.748 | C9: 257072.37 | D9: 118790.29 | E9: 119376.22
A10: Samedi | B10: 53649.374 | C10: 214329.27 | D10: 117917.91 | E10: 103162.48
A11: Dimanche | B11: 60408.908 | C11: 205476.19 | D11: 117969.29 | E11: 104157.51
A12: Total général | B12: 61059.086 | C12: 242237.07 | D12: 117349.81 | E12: 111342.57
A15: Quels sont les jours de la semaine les plus rentables en termes de chiffre d’affaires et de
A16: volume de vente ?
A18: Étiquettes de lignes | B18: Somme de Unité vendu | C18: Somme de Total vente
A19: Mardi | B19: 375302 | C19: 137138087
A20: Mercredi | B20: 349356 | C20: 120114465
A21: Jeudi | B21: 371771 | C21: 145683120
A22: Vendredi | B22: 381379 | C22: 146683099
A23: Total général | B23: 1477808 | C23: 549618771

Sheet Dashboard
A1: Tableau de bord interactif des ventes de KIN MARCHE USA
A5: Dernière mise à jour : | D5: CA total ($) | H5: Unités vendues | L5: Bénéfice d'exploitation ($) | P5: Marge d'exploitation
A6: 25/10/2026 | D6: =SUM(donneesVentes!$U:$U) -> 899902125 | H6: =SUM(donneesVentes!$V:$V) -> 2478861 | L6: =SUM(donneesVentes!$W:$W) -> 3.3213476e+08 | P6: =IF($D$6=0,0,$L$6/$D$6) -> 0.36907876

Sheet donneesVentes
A1: Détaillant | B1: ID Détailant | C1: Date Facture | D1: Jours | E1: Region | F1: Etat | G1: Ville | H1: Produit | I1: Vente par unité | J1: Unité vendu | K1: Total vente | L1: Bénéfice d'exploitation | M1: Marge d'exploitation | N1: Méthode de vente | O1: Année | P1: MoisNum | Q1: MoisNom | R1: EtatEN | S1: AnneeMois | T1: Inclus | U1: CA filtré | V1: Unités filtrées | W1: Bénéfice filtré
A2: Foot Locker | B2: 1185732 | C2: 43831 | D2: {=_xlfn.SWITCH(WEEKDAY(C2,2), 1, "Lundi", 2, "Mardi", 3, "Mercredi", 4, "Jeudi", 5, "Vendredi", 6, "Samedi", 7, "Dimanche", "Erreur")} -> Mercredi | E2: Nord-est | F2: New York | G2: New York | H2: Chaussures de rue pour hommes | I2: 50 | J2: 1200 | K2: 600000 | L2: 300000 | M2: 0.5 | N2: En magasin | O2: =YEAR($C2) -> 2020 | P2: =MONTH($C2) -> 1 | Q2: =TEXT($C2,"mmm") -> janv | R2: =SUBSTITUTE(SUBSTITUTE($F2,"Sud ","South "),"Ouest ","West ") -> New York | S2: =TEXT($C2,"aaaa-mm") -> 2020-01 | T2: =IF(AND(COUNTIF(Calculs!$Q$2:$Q$12,$O2)>0,COUNTIF(Calculs!$S$2:$S$12,$E2)>0,COUNTIF(Calculs!$U$2:$U$12,$H2)>0),1,0) -> 1 | U2: =$K2*$T2 -> 600000 | V2: =$J2*$T2 -> 1200 | W2: =$L2*$T2 -> 300000
A3: Foot Locker | B3: 1185732 | C3: 43832 | D3: {=_xlfn.SWITCH(WEEKDAY(C3,2), 1, "Lundi", 2, "Mardi", 3, "Mercredi", 4, "Jeudi", 5, "Vendredi", 6, "Samedi", 7, "Dimanche", "Erreur")} -> Jeudi | E3: Nord-est | F3: New York | G3: New York | H3: Chaussures de sport pour hommes | I3: 50 | J3: 1000 | K3: 500000 | L3: 150000 | M3: 0.3 | N3: En magasin | O3: =YEAR($C3) -> 2020 | P3: =MONTH($C3) -> 1 | Q3: =TEXT($C3,"mmm") -> janv | R3: =SUBSTITUTE(SUBSTITUTE($F3,"Sud ","South "),"Ouest ","West ") -> New York | S3: =TEXT($C3,"aaaa-mm") -> 2020-01 | T3: =IF(AND(COUNTIF(Calculs!$Q$2:$Q$12,$O3)>0,COUNTIF(Calculs!$S$2:$S$12,$E3)>0,COUNTIF(Calculs!$U$2:$U$12,$H3)>0),1,0) -> 1 | U3: =$K3*$T3 -> 500000 | V3: =$J3*$T3 -> 1000 | W3: =$L3*$T3 -> 150000
A4: Foot Locker | B4: 1185732 | C4: 43833 | D4: {=_xlfn.SWITCH(WEEKDAY(C4,2), 1, "Lundi", 2, "Mardi", 3, "Mercredi", 4, "Jeudi", 5, "Vendredi", 6, "Samedi", 7, "Dimanche", "Erreur")} -> Vendredi | E4: Nord-est | F4: New York | G4: New York | H4: Chaussures de rue pour femmes | I4: 40 | J4: 1000 | K4: 400000 | L4: 140000 | M4: 0.35 | N4: En magasin | O4: =YEAR($C4) -> 2020 | P4: =MONTH($C4) -> 1 | Q4: =TEXT($C4,"mmm") -> janv | R4: =SUBSTITUTE(SUBSTITUTE($F4,"Sud ","South "),"Ouest ","West ") -> New York | S4: =TEXT($C4,"aaaa-mm") -> 2020-01 | T4: =IF(AND(COUNTIF(Calculs!$Q$2:$Q$12,$O4)>0,COUNTIF(Calculs!$S$2:$S$12,$E4)>0,COUNTIF(Calculs!$U$2:$U$12,$H4)>0),1,0) -> 1 | U4: =$K4*$T4 -> 400000 | V4: =$J4*$T4 -> 1000 | W4: =$L4*$T4 -> 140000
A5: Foot Locker | B5: 1185732 | C5: 43834 | D5: {=_xlfn.SWITCH(WEEKDAY(C5,2), 1, "Lundi", 2, "Mardi", 3, "Mercredi", 4, "Jeudi", 5, "Vendredi", 6, "Samedi", 7, "Dimanche", "Erreur")} -> Samedi | E5: Nord-est | F5: New York | G5: New York | H5: Chaussures de sport pour femmes | I5: 45 | J5: 850 | K5: 382500 | L5: 133875 | M5: 0.35 | N5: En magasin | O5: =YEAR($C5) -> 2020 | P5: =MONTH($C5) -> 1 | Q5: =TEXT($C5,"mmm") -> janv | R5: =SUBSTITUTE(SUBSTITUTE($F5,"Sud ","South "),"Ouest ","West ") -> New York | S5: =TEXT($C5,"aaaa-mm") -> 2020-01 | T5: =IF(AND(COUNTIF(Calculs!$Q$2:$Q$12,$O5)>0,COUNTIF(Calculs!$S$2:$S$12,$E5)>0,COUNTIF(Calculs!$U$2:$U$12,$H5)>0),1,0) -> 1 | U5: =$K5*$T5 -> 382500 | V5: =$J5*$T5 -> 850 | W5: =$L5*$T5 -> 133875
A6: Foot Locker | B6: 1185732 | C6: 43835 | D6: {=_xlfn.SWITCH(WEEKDAY(C6,2), 1, "Lundi", 2, "Mardi", 3, "Mercredi", 4, "Jeudi", 5, "Vendredi", 6, "Samedi", 7, "Dimanche", "Erreur")} -> Dimanche | E6: Nord-est | F6: New York | G6: New York | H6: Vêtements pour hommes | I6: 60 | J6: 900 | K6: 540000 | L6: 162000 | M6: 0.3 | N6: En magasin | O6: =YEAR($C6) -> 2020 | P6: =MONTH($C6) -> 1 | Q6: =TEXT($C6,"mmm") -> janv | R6: =SUBSTITUTE(SUBSTITUTE($F6,"Sud ","South "),"Ouest ","West ") -> New York | S6: =TEXT($C6,"aaaa-mm") -> 2020-01 | T6: =IF(AND(COUNTIF(Calculs!$Q$2:$Q$12,$O6)>0,COUNTIF(Calculs!$S$2:$S$12,$E6)>0,COUNTIF(Calculs!$U$2:$U$12,$H6)>0),1,0) -> 1 | U6: =$K6*$T6 -> 540000 | V6: =$J6*$T6 -> 900 | W6: =$L6*$T6 -> 162000
A7: Foot Locker | B7: 1185732 | C7: 43836 | D7: {=_xlfn.SWITCH(WEEKDAY(C7,2), 1, "Lundi", 2, "Mardi", 3, "Mercredi", 4, "Jeudi", 5, "Vendredi", 6, "Samedi", 7, "Dimanche", "Erreur")} -> Lundi | E7: Nord-est | F7: New York | G7: New York | H7: Vêtements pour femmes | I7: 50 | J7: 1000 | K7: 500000 | L7: 125000 | M7: 0.25 | N7: En magasin | O7: =YEAR($C7) -> 2020 | P7: =MONTH($C7) -> 1 | Q7: =TEXT($C7,"mmm") -> janv | R7: =SUBSTITUTE(SUBSTITUTE($F7,"Sud ","South "),"Ouest ","West ") -> New York | S7: =TEXT($C7,"aaaa-mm") -> 2020-01 | T7: =IF(AND(COUNTIF(Calculs!$Q$2:$Q$12,$O7)>0,COUNTIF(Calculs!$S$2:$S$12,$E7)>0,COUNTIF(Calculs!$U$2:$U$12,$H7)>0),1,0) -> 1 | U7: =$K7*$T7 -> 500000 | V7: =$J7*$T7 -> 1000 | W7: =$L7*$T7 -> 125000
A8: Foot Locker | B8: 1185732 | C8: 43837 | D8: {=_xlfn.SWITCH(WEEKDAY(C8,2), 1, "Lundi", 2, "Mardi", 3, "Mercredi", 4, "Jeudi", 5, "Vendredi", 6, "Samedi", 7, "Dimanche", "Erreur")} -> Mardi | E8: Nord-est | F8: New York | G8: New York | H8: Chaussures de rue pour hommes | I8: 50 | J8: 1250 | K8: 625000 | L8: 312500 | M8: 0.5 | N8: En magasin | O8: =YEAR($C8) -> 2020 | P8: =MONTH($C8) -> 1 | Q8: =TEXT($C8,"mmm") -> janv | R8: =SUBSTITUTE(SUBSTITUTE($F8,"Sud ","South "),"Ouest ","West ") -> New York | S8: =TEXT($C8,"aaaa-mm") -> 2020-01 | T8: =IF(AND(COUNTIF(Calculs!$Q$2:$Q$12,$O8)>0,COUNTIF(Calculs!$S$2:$S$12,$E8)>0,COUNTIF(Calculs!$U$2:$U$12,$H8)>0),1,0) -> 1 | U8: =$K8*$T8 -> 625000 | V8: =$J8*$T8 -> 1250 | W8: =$L8*$T8 -> 312500
A9: Foot Locker | B9: 1185732 | C9: 43838 | D9: {=_xlfn.SWITCH(WEEKDAY(C9,2), 1, "Lundi", 2, "Mardi", 3, "Mercredi", 4, "Jeudi", 5, "Vendredi", 6, "Samedi", 7, "Dimanche", "Erreur")} -> Mercredi | E9: Nord-est | F9: New York | G9: New York | H9: Chaussures de sport pour hommes | I9: 50 | J9: 900 | K9: 450000 | L9: 135000 | M9: 0.3 | N9: Sortie | O9: =YEAR($C9) -> 2020 | P9: =MONTH($C9) -> 1 | Q9: =TEXT($C9,"mmm") -> janv | R9: =SUBSTITUTE(SUBSTITUTE($F9,"Sud ","South "),"Ouest ","West ") -> New York | S9: =TEXT($C9,"aaaa-mm") -> 2020-01 | T9: =IF(AND(COUNTIF(Calculs!$Q$2:$Q$12,$O9)>0,COUNTIF(Calculs!$S$2:$S$12,$E9)>0,COUNTIF(Calculs!$U$2:$U$12,$H9)>0),1,0) -> 1 | U9: =$K9*$T9 -> 450000 | V9: =$J9*$T9 -> 900 | W9: =$L9*$T9 -> 135000
A10: Foot Locker | B10: 1185732 | C10: 43851 | D10: {=_xlfn.SWITCH(WEEKDAY(C10,2), 1, "Lundi", 2, "Mardi", 3, "Mercredi", 4, "Jeudi", 5, "Vendredi", 6, "Samedi", 7, "Dimanche", "Erreur")} -> Mardi | E10: Nord-est | F10: New York | G10: New York | H10: Chaussures de rue pour femmes | I10: 40 | J10: 950 | K10: 380000 | L10: 133000 | M10: 0.35 | N10: Sortie | O10: =YEAR($C10) -> 2020 | P10: =MONTH($C10) -> 1 | Q10: =TEXT($C10,"mmm") -> janv | R10: =SUBSTITUTE(SUBSTITUTE($F10,"Sud ","South "),"Ouest ","West ") -> New York | S10: =TEXT($C10,"aaaa-mm") -> 2020-01 | T10: =IF(AND(COUNTIF(Calculs!$Q$2:$Q$12,$O10)>0,COUNTIF(Calculs!$S$2:$S$12,$E10)>0,COUNTIF(Calculs!$U$2:$U$12,$H10)>0),1,0) -> 1 | U10: =$K10*$T10 -> 380000 | V10: =$J10*$T10 -> 950 | W10: =$L10*$T10 -> 133000
A11: Foot Locker | B11: 1185732 | C11: 43852 | D11: {=_xlfn.SWITCH(WEEKDAY(C11,2), 1, "Lundi", 2, "Mardi", 3, "Mercredi", 4, "Jeudi", 5, "Vendredi", 6, "Samedi", 7, "Dimanche", "Erreur")} -> Mercredi | E11: Nord-est | F11: New York | G11: New York | H11: Chaussures de sport pour femmes | I11: 45 | J11: 825 | K11: 371250 | L11: 129937.5 | M11: 0.35 | N11: Sortie | O11: =YEAR($C11) -> 2020 | P11: =MONTH($C11) -> 1 | Q11: =TEXT($C11,"mmm") -> janv | R11: =SUBSTITUTE(SUBSTITUTE($F11,"Sud ","South "),"Ouest ","West ") -> New York | S11: =TEXT($C11,"aaaa-mm") -> 2020-01 | T11: =IF(AND(COUNTIF(Calculs!$Q$2:$Q$12,$O11)>0,COUNTIF(Calculs!$S$2:$S$12,$E11)>0,COUNTIF(Calculs!$U$2:$U$12,$H11)>0),1,0) -> 1 | U11: =$K11*$T11 -> 371250 | V11: =$J11*$T11 -> 825 | W11: =$L11*$T11 -> 129937.5
A12: Foot Locker | B12: 1185732 | C12: 43853 | D12: {=_xlfn.SWITCH(WEEKDAY(C12,2), 1, "Lundi", 2, "Mardi", 3, "Mercredi", 4, "Jeudi", 5, "Vendredi", 6, "Samedi", 7, "Dimanche", "Erreur")} -> Jeudi | E12: Nord-est | F12: New York | G12: New York | H12: Vêtements pour hommes | I12: 60 | J12: 900 | K12: 540000 | L12: 162000 | M12: 0.3 | N12: Sortie | O12: =YEAR($C12) -> 2020 | P12: =MONTH($C12) -> 1 | Q12: =TEXT($C12,"mmm") -> janv | R12: =SUBSTITUTE(SUBSTITUTE($F12,"Sud ","South "),"Ouest ","West ") -> New York | S12: =TEXT($C12,"aaaa-mm") -> 2020-01 | T12: =IF(AND(COUNTIF(Calculs!$Q$2:$Q$12,$O12)>0,COUNTIF(Calculs!$S$2:$S$12,$E12)>0,COUNTIF(Calculs!$U$2:$U$12,$H12)>0),1,0) -> 1 | U12: =$K12*$T12 -> 540000 | V12: =$J12*$T12 -> 900 | W12: =$L12*$T12 -> 162000
A13: Foot Locker | B13: 1185732 | C13: 43854 | D13: {=_xlfn.SWITCH(WEEKDAY(C13,2), 1, "Lundi", 2, "Mardi", 3, "Mercredi", 4, "Jeudi", 5, "Vendredi", 6, "Samedi", 7, "Dimanche", "Erreur")} -> Vendredi | E13: Nord-est | F13: New York | G13: New York | H13: Vêtements pour femmes | I13: 50 | J13: 1000 | K13: 500000 | L13: 125000 | M13: 0.25 | N13: Sortie | O13: =YEAR($C13) -> 2020 | P13: =MONTH($C13) -> 1 | Q13: =TEXT($C13,"mmm") -> janv | R13: =SUBSTITUTE(SUBSTITUTE($F13,"Sud ","South "),"Ouest ","West ") -> New York | S13: =TEXT($C13,"aaaa-mm") -> 2020-01 | T13: =IF(AND(COUNTIF(Calculs!$Q$2:$Q$12,$O13)>0,COUNTIF(Calculs!$S$2:$S$12,$E13)>0,COUNTIF(Calculs!$U$2:$U$12,$H13)>0),1,0) -> 1 | U13: =$K13*$T13 -> 500000 | V13: =$J13*$T13 -> 1000 | W13: =$L13*$T13 -> 125000
... A9649: Foot Locker | B9649: 1185732 | C9649: 44249 | D9649: {=_xlfn.SWITCH(WEEKDAY(C9649,2), 1, "Lundi", 2, "Mardi", 3, "Mercredi", 4, "Jeudi", 5, "Vendredi", 6, "Samedi", 7, "Dimanche", "Erreur")} -> Lundi | E9649: Nord-est | F9649: New Hampshire | G9649: Manchester | H9649: Chaussures de rue pour femmes | I9649: 29 | J9649: 83 | K9649: 2407 | L9649: 649.89 | M9649: 0.27 | N9649: Sortie | O9649: =YEAR($C9649) -> 2021 | P9649: =MONTH($C9649) -> 2 | Q9649: =TEXT($C9649,"mmm") -> févr | R9649: =SUBSTITUTE(SUBSTITUTE($F9649,"Sud ","South "),"Ouest ","West ") -> New Hampshire | S9649: =TEXT($C9649,"aaaa-mm") -> 2021-02 | T9649: =IF(AND(COUNTIF(Calculs!$Q$2:$Q$12,$O9649)>0,COUNTIF(Calculs!$S$2:$S$12,$E9649)>0,COUNTIF(Calculs!$U$2:$U$12,$H9649)>0),1,0) -> 1 | U9649: =$K9649*$T9649 -> 2407 | V9649: =$J9649*$T9649 -> 83 | W9649: =$L9649*$T9649 -> 649.89

Sheet Calculs
A1: Clé | B1: Mois | C1: CA (M$) | E1: Etat | F1: CA (M$) | H1: Méthode de vente | I1: CA (M$) | K1: Détaillant | L1: CA (M$) | N1: Détaillant (source) | O1: CA (M$) | Q1: Étiquettes de lignes | S1: Étiquettes de lignes | U1: Étiquettes de lignes | X1: Année | Y1: Région | Z1: Produit
A2: =TEXT(DATE(2020,ROW()-1,1),"aaaa-mm") -> 2020-01 | B2: =TEXT(DATE(2020,ROW()-1,1),"mmm aa") -> janv 20 | C2: =SUMIF(donneesVentes!$S:$S,$A2,donneesVentes!$U:$U)/1000000 -> 16.253746 | E2: Alabama | F2: =SUMIF(donneesVentes!$R:$R,$E2,donneesVentes!$U:$U)/1000000 -> 17.633424 | H2: En ligne | I2: =SUMIF(donneesVentes!$N:$N,$H2,donneesVentes!$U:$U)/1000000 -> 247.67288 | K2: =INDEX($N$2:$N$7,MATCH(SMALL($O$2:$O$7,ROW()-1),$O$2:$O$7,0)) -> Walmart | L2: =SMALL($O$2:$O$7,ROW()-1) -> 74.55841 | N2: Amazon | O2: =SUMIF(donneesVentes!$A:$A,$N2,donneesVentes!$U:$U)/1000000 -> 77.698912 | Q2: 2020 | S2: Milieu ouest | U2: Chaussures de rue pour femmes | X2: 2020 | Y2: Milieu ouest | Z2: Chaussures de rue pour femmes
A3: =TEXT(DATE(2020,ROW()-1,1),"aaaa-mm") -> 2020-02 | B3: =TEXT(DATE(2020,ROW()-1,1),"mmm aa") -> févr 20 | C3: =SUMIF(donneesVentes!$S:$S,$A3,donneesVentes!$U:$U)/1000000 -> 14.997988 | E3: Alaska | F3: =SUMIF(donneesVentes!$R:$R,$E3,donneesVentes!$U:$U)/1000000 -> 14.753103 | H3: En magasin | I3: =SUMIF(donneesVentes!$N:$N,$H3,donneesVentes!$U:$U)/1000000 -> 356.64375 | K3: =INDEX($N$2:$N$7,MATCH(SMALL($O$2:$O$7,ROW()-1),$O$2:$O$7,0)) -> Amazon | L3: =SMALL($O$2:$O$7,ROW()-1) -> 77.698912 | N3: Foot Locker | O3: =SUMIF(donneesVentes!$A:$A,$N3,donneesVentes!$U:$U)/1000000 -> 220.09472 | Q3: 2021 | S3: Nord-est | U3: Chaussures de rue pour hommes | X3: 2021 | Y3: Nord-est | Z3: Chaussures de rue pour hommes
A4: =TEXT(DATE(2020,ROW()-1,1),"aaaa-mm") -> 2020-03 | B4: =TEXT(DATE(2020,ROW()-1,1),"mmm aa") -> mars 20 | C4: =SUMIF(donneesVentes!$S:$S,$A4,donneesVentes!$U:$U)/1000000 -> 17.660577 | E4: Arizona | F4: =SUMIF(donneesVentes!$R:$R,$E4,donneesVentes!$U:$U)/1000000 -> 15.782221 | H4: Sortie | I4: =SUMIF(donneesVentes!$N:$N,$H4,donneesVentes!$U:$U)/1000000 -> 295.58549 | K4: =INDEX($N$2:$N$7,MATCH(SMALL($O$2:$O$7,ROW()-1),$O$2:$O$7,0)) -> Kohl's | L4: =SMALL($O$2:$O$7,ROW()-1) -> 102.11475 | N4: Kohl's | O4: =SUMIF(donneesVentes!$A:$A,$N4,donneesVentes!$U:$U)/1000000 -> 102.11475 | Q4: Total général | S4: Ouest | U4: Chaussures de sport pour femmes | Y4: Ouest | Z4: Chaussures de sport pour femmes
A5: =TEXT(DATE(2020,ROW()-1,1),"aaaa-mm") -> 2020-04 | B5: =TEXT(DATE(2020,ROW()-1,1),"mmm aa") -> avr 20 | C5: =SUMIF(donneesVentes!$S:$S,$A5,donneesVentes!$U:$U)/1000000 -> 24.607006 | E5: Arkansas | F5: =SUMIF(donneesVentes!$R:$R,$E5,donneesVentes!$U:$U)/1000000 -> 12.639347 | K5: =INDEX($N$2:$N$7,MATCH(SMALL($O$2:$O$7,ROW()-1),$O$2:$O$7,0)) -> Sports Direct | L5: =SMALL($O$2:$O$7,ROW()-1) -> 182.471 | N5: Ouest Gear | O5: =SUMIF(donneesVentes!$A:$A,$N5,donneesVentes!$U:$U)/1000000 -> 242.96433 | S5: Sud | U5: Chaussures de sport pour hommes | Y5: Sud | Z5: Chaussures de sport pour hommes
A6: =TEXT(DATE(2020,ROW()-1,1),"aaaa-mm") -> 2020-05 | B6: =TEXT(DATE(2020,ROW()-1,1),"mmm aa") -> mai 20 | C6: =SUMIF(donneesVentes!$S:$S,$A6,donneesVentes!$U:$U)/1000000 -> 16.918014 | E6: California | F6: =SUMIF(donneesVentes!$R:$R,$E6,donneesVentes!$U:$U)/1000000 -> 60.174133 | K6: =INDEX($N$2:$N$7,MATCH(SMALL($O$2:$O$7,ROW()-1),$O$2:$O$7,0)) -> Foot Locker | L6: =SMALL($O$2:$O$7,ROW()-1) -> 220.09472 | N6: Sports Direct | O6: =SUMIF(donneesVentes!$A:$A,$N6,donneesVentes!$U:$U)/1000000 -> 182.471 | S6: Sud-est | U6: Vêtements pour femmes | Y6: Sud-est | Z6: Vêtements pour femmes
A7: =TEXT(DATE(2020,ROW()-1,1),"aaaa-mm") -> 2020-06 | B7: =TEXT(DATE(2020,ROW()-1,1),"mmm aa") -> juin 20 | C7: =SUMIF(donneesVentes!$S:$S,$A7,donneesVentes!$U:$U)/1000000 -> 8.829819 | E7: Colorado | F7: =SUMIF(donneesVentes!$R:$R,$E7,donneesVentes!$U:$U)/1000000 -> 20.996536 | K7: =INDEX($N$2:$N$7,MATCH(SMALL($O$2:$O$7,ROW()-1),$O$2:$O$7,0)) -> Ouest Gear | L7: =SMALL($O$2:$O$7,ROW()-1) -> 242.96433 | N7: Walmart | O7: =SUMIF(donneesVentes!$A:$A,$N7,donneesVentes!$U:$U)/1000000 -> 74.55841 | S7: Total général | U7: Vêtements pour hommes | Z7: Vêtements pour hommes
A8: =TEXT(DATE(2020,ROW()-1,1),"aaaa-mm") -> 2020-07 | B8: =TEXT(DATE(2020,ROW()-1,1),"mmm aa") -> juil 20 | C8: =SUMIF(donneesVentes!$S:$S,$A8,donneesVentes!$U:$U)/1000000 -> 17.146013 | E8: Connecticut | F8: =SUMIF(donneesVentes!$R:$R,$E8,donneesVentes!$U:$U)/1000000 -> 11.573448 | U8: Total général
A9: =TEXT(DATE(2020,ROW()-1,1),"aaaa-mm") -> 2020-08 | B9: =TEXT(DATE(2020,ROW()-1,1),"mmm aa") -> août 20 | C9: =SUMIF(donneesVentes!$S:$S,$A9,donneesVentes!$U:$U)/1000000 -> 19.87798 | E9: Delaware | F9: =SUMIF(donneesVentes!$R:$R,$E9,donneesVentes!$U:$U)/1000000 -> 12.298412
A10: =TEXT(DATE(2020,ROW()-1,1),"aaaa-mm") -> 2020-09 | B10: =TEXT(DATE(2020,ROW()-1,1),"mmm aa") -> sept 20 | C10: =SUMIF(donneesVentes!$S:$S,$A10,donneesVentes!$U:$U)/1000000 -> 18.304436 | E10: Florida | F10: =SUMIF(donneesVentes!$R:$R,$E10,donneesVentes!$U:$U)/1000000 -> 59.283714
A11: =TEXT(DATE(2020,ROW()-1,1),"aaaa-mm") -> 2020-10 | B11: =TEXT(DATE(2020,ROW()-1,1),"mmm aa") -> oct 20 | C11: =SUMIF(donneesVentes!$S:$S,$A11,donneesVentes!$U:$U)/1000000 -> 10.836269 | E11: Georgia | F11: =SUMIF(donneesVentes!$R:$R,$E11,donneesVentes!$U:$U)/1000000 -> 18.997466
A12: =TEXT(DATE(2020,ROW()-1,1),"aaaa-mm") -> 2020-11 | B12: =TEXT(DATE(2020,ROW()-1,1),"mmm aa") -> nov 20 | C12: =SUMIF(donneesVentes!$S:$S,$A12,donneesVentes!$U:$U)/1000000 -> 8.6223 | E12: Hawaii | F12: =SUMIF(donneesVentes!$R:$R,$E12,donneesVentes!$U:$U)/1000000 -> 22.282457
A13: =TEXT(DATE(2020,ROW()-1,1),"aaaa-mm") -> 2020-12 | B13: =TEXT(DATE(2020,ROW()-1,1),"mmm aa") -> déc 20 | C13: =SUMIF(donneesVentes!$S:$S,$A13,donneesVentes!$U:$U)/1000000 -> 8.026527 | E13: Idaho | F13: =SUMIF(donneesVentes!$R:$R,$E13,donneesVentes!$U:$U)/1000000 -> 19.276878
A14: =TEXT(DATE(2020,ROW()-1,1),"aaaa-mm") -> 2021-01 | B14: =TEXT(DATE(2020,ROW()-1,1),"mmm aa") -> janv 21 | C14: =SUMIF(donneesVentes!$S:$S,$A14,donneesVentes!$U:$U)/1000000 -> 55.225396 | E14: Illinois | F14: =SUMIF(donneesVentes!$R:$R,$E14,donneesVentes!$U:$U)/1000000 -> 9.797488
A15: =TEXT(DATE(2020,ROW()-1,1),"aaaa-mm") -> 2021-02 | B15: =TEXT(DATE(2020,ROW()-1,1),"mmm aa") -> févr 21 | C15: =SUMIF(donneesVentes!$S:$S,$A15,donneesVentes!$U:$U)/1000000 -> 46.102165 | E15: Indiana | F15: =SUMIF(donneesVentes!$R:$R,$E15,donneesVentes!$U:$U)/1000000 -> 8.836198
A16: =TEXT(DATE(2020,ROW()-1,1),"aaaa-mm") -> 2021-03 | B16: =TEXT(DATE(2020,ROW()-1,1),"mmm aa") -> mars 21 | C16: =SUMIF(donneesVentes!$S:$S,$A16,donneesVentes!$U:$U)/1000000 -> 39.148532 | E16: Iowa | F16: =SUMIF(donneesVentes!$R:$R,$E16,donneesVentes!$U:$U)/1000000 -> 7.424011
A17: =TEXT(DATE(2020,ROW()-1,1),"aaaa-mm") -> 2021-04 | B17: =TEXT(DATE(2020,ROW()-1,1),"mmm aa") -> avr 21 | C17: =SUMIF(donneesVentes!$S:$S,$A17,donneesVentes!$U:$U)/1000000 -> 47.732964 | E17: Kansas | F17: =SUMIF(donneesVentes!$R:$R,$E17,donneesVentes!$U:$U)/1000000 -> 9.972864
A18: =TEXT(DATE(2020,ROW()-1,1),"aaaa-mm") -> 2021-05 | B18: =TEXT(DATE(2020,ROW()-1,1),"mmm aa") -> mai 21 | C18: =SUMIF(donneesVentes!$S:$S,$A18,donneesVentes!$U:$U)/1000000 -> 63.589681 | E18: Kentucky | F18: =SUMIF(donneesVentes!$R:$R,$E18,donneesVentes!$U:$U)/1000000 -> 10.072848
A19: =TEXT(DATE(2020,ROW()-1,1),"aaaa-mm") -> 2021-06 | B19: =TEXT(DATE(2020,ROW()-1,1),"mmm aa") -> juin 21 | C19: =SUMIF(donneesVentes!$S:$S,$A19,donneesVentes!$U:$U)/1000000 -> 65.917553 | E19: Louisiana | F19: =SUMIF(donneesVentes!$R:$R,$E19,donneesVentes!$U:$U)/1000000 -> 23.750781
A20: =TEXT(DATE(2020,ROW()-1,1),"aaaa-mm") -> 2021-07 | B20: =TEXT(DATE(2020,ROW()-1,1),"mmm aa") -> juil 21 | C20: =SUMIF(donneesVentes!$S:$S,$A20,donneesVentes!$U:$U)/1000000 -> 78.334681 | E20: Maine | F20: =SUMIF(donneesVentes!$R:$R,$E20,donneesVentes!$U:$U)/1000000 -> 9.195978
... A25: =TEXT(DATE(2020,ROW()-1,1),"aaaa-mm") -> 2021-12 | B25: =TEXT(DATE(2020,ROW()-1,1),"mmm aa") -> déc 21 | C25: =SUMIF(donneesVentes!$S:$S,$A25,donneesVentes!$U:$U)/1000000 -> 77.81543 | E25: Mississippi | F25: =SUMIF(donneesVentes!$R:$R,$E25,donneesVentes!$U:$U)/1000000 -> 15.591709
E26: Missouri | F26: =SUMIF(donneesVentes!$R:$R,$E26,donneesVentes!$U:$U)/1000000 -> 9.683265
E27: Montana | F27: =SUMIF(donneesVentes!$R:$R,$E27,donneesVentes!$U:$U)/1000000 -> 15.710886
E28: Nebraska | F28: =SUMIF(donneesVentes!$R:$R,$E28,donneesVentes!$U:$U)/1000000 -> 5.929038
E29: Nevada | F29: =SUMIF(donneesVentes!$R:$R,$E29,donneesVentes!$U:$U)/1000000 -> 20.858509
E30: New Hampshire | F30: =SUMIF(donneesVentes!$R:$R,$E30,donneesVentes!$U:$U)/1000000 -> 16.411667
E31: New Jersey | F31: =SUMIF(donneesVentes!$R:$R,$E31,donneesVentes!$U:$U)/1000000 -> 9.934246
E32: New Mexico | F32: =SUMIF(donneesVentes!$R:$R,$E32,donneesVentes!$U:$U)/1000000 -> 19.865016
E33: New York | F33: =SUMIF(donneesVentes!$R:$R,$E33,donneesVentes!$U:$U)/1000000 -> 64.229039
E34: North Carolina | F34: =SUMIF(donneesVentes!$R:$R,$E34,donneesVentes!$U:$U)/1000000 -> 23.956531
E35: North Dakota | F35: =SUMIF(donneesVentes!$R:$R,$E35,donneesVentes!$U:$U)/1000000 -> 7.73558
E36: Ohio | F36: =SUMIF(donneesVentes!$R:$R,$E36,donneesVentes!$U:$U)/1000000 -> 18.484583
E37: Oklahoma | F37: =SUMIF(donneesVentes!$R:$R,$E37,donneesVentes!$U:$U)/1000000 -> 10.620734
... E51: Wyoming | F51: =SUMIF(donneesVentes!$R:$R,$E51,donneesVentes!$U:$U)/1000000 -> 18.577517
